Metadata-Version: 2.1
Name: pydyno
Version: 0.1.2
Summary: Dynamic analysis of systems biology models
Home-page: UNKNOWN
Author: Oscar Ortega
Author-email: oscar.ortega@vanderbilt.edu
License: UNKNOWN
Keywords: systems,biology,model
Platform: UNKNOWN
Classifier: Development Status :: 4 - Beta
Classifier: Environment :: Console
Classifier: Intended Audience :: Science/Research
Classifier: License :: OSI Approved :: MIT License
Classifier: Operating System :: OS Independent
Classifier: Programming Language :: Python :: 3
Classifier: Topic :: Scientific/Engineering :: Bio-Informatics
Classifier: Topic :: Scientific/Engineering :: Chemistry
Classifier: Topic :: Scientific/Engineering :: Mathematics
Requires-Dist: pysb
Requires-Dist: matplotlib
Requires-Dist: anytree
Requires-Dist: scikit-learn
Requires-Dist: pydot
Requires-Dist: tqdm
Requires-Dist: editdistance
Requires-Dist: pandas
Requires-Dist: networkx
Requires-Dist: numpy
Requires-Dist: sympy (==1.5)
